textual_nerv/__init__.py
textual_nerv/theme.py
textual_nerv-0.1.2.dist-info/METADATA
textual_nerv-0.1.2.dist-info/WHEEL
textual_nerv-0.1.2.dist-info/licenses/LICENSE
textual_nerv-0.1.2.dist-info/RECORD
